starsessions/__init__.py
starsessions/exceptions.py
starsessions/middleware.py
starsessions/py.typed
starsessions/serializers.py
starsessions/session.py
starsessions/stores/__init__.py
starsessions/stores/base.py
starsessions/stores/cookie.py
starsessions/stores/memory.py
starsessions/stores/redis.py
starsessions/types.py
starsessions-2.2.0.dist-info/LICENSE
starsessions-2.2.0.dist-info/METADATA
starsessions-2.2.0.dist-info/WHEEL
starsessions-2.2.0.dist-info/RECORD
