Metadata-Version: 2.1
Name: starsessions
Version: 2.2.0
Summary: Advanced sessions for Starlette and FastAPI frameworks
Home-page: https://github.com/alex-oleshkevich/starsessions
License: MIT
Keywords: starlette,fastapi,asgi,session
Author: alex.oleshkevich
Author-email: alex.oleshkevich@gmail.com
Requires-Python: >=3.8.0,<4.0.0
Classifier: Development Status :: 5 - Production/Stable
Classifier: Environment :: Web Environment
Classifier: Intended Audience :: Developers
Classifier: License :: OSI Approved :: MIT License
Classifier: Operating System :: OS Independent
Classifier: Programming Language :: Python :: 3
Classifier: Programming Language :: Python :: 3.8
Classifier: Programming Language :: Python :: 3.9
Classifier: Programming Language :: Python :: 3.10
Classifier: Programming Language :: Python :: 3.11
Classifier: Programming Language :: Python :: 3.12
Classifier: Programming Language :: Python :: 3.13
Classifier: Topic :: Software Development :: Libraries
Classifier: Typing :: Typed
Provides-Extra: redis
Requires-Dist: itsdangerous (>=2,<3)
Requires-Dist: redis (>=4.2.0rc1) ; extra == "redis"
Requires-Dist: starlette
Project-URL: Documentation, https://github.com/alex-oleshkevich/starsessions
Project-URL: Repository, https://github.com/alex-oleshkevich/starsessions
